setup.py
libreoffice_convert/__init__.py
libreoffice_convert/commands.py
libreoffice_convert/converter.py
libreoffice_convert/document_types.py
libreoffice_convert.egg-info/PKG-INFO
libreoffice_convert.egg-info/SOURCES.txt
libreoffice_convert.egg-info/dependency_links.txt
libreoffice_convert.egg-info/entry_points.txt
libreoffice_convert.egg-info/top_level.txt