Metadata-Version: 1.1
Name: libreoffice-convert
Version: 1.0
Summary: Python module using LibreOffice API to convert file format to another file format
Home-page: http://ferdinandsilva.com
Author: Ferdinand Silva
Author-email: ferdinandsilva@ferdinandsilva.com
License: UNKNOWN
Download-URL: http://ferdinandsilva.com
Platform: UNKNOWN
Classifier: Development Status :: 4 - Beta
Classifier: Intended Audience :: Developers
Classifier: Natural Language :: English
Classifier: Programming Language :: Python
Classifier: Programming Language :: Python :: 3
Classifier: License :: Freeware
